nativeauthenticator/__init__.py
nativeauthenticator/common-credentials.txt
nativeauthenticator/handlers.py
nativeauthenticator/nativeauthenticator.py
nativeauthenticator/orm.py
nativeauthenticator/crypto/__init__.py
nativeauthenticator/crypto/crypto.py
nativeauthenticator/crypto/encoding.py
nativeauthenticator/crypto/signing.py
nativeauthenticator/templates/authorization-area.html
nativeauthenticator/templates/change-password-admin.html
nativeauthenticator/templates/change-password.html
nativeauthenticator/templates/my_message.html
nativeauthenticator/templates/native-login.html
nativeauthenticator/templates/page.html
nativeauthenticator/templates/signup.html
nativeauthenticator/tests/__init__.py
nativeauthenticator/tests/conftest.py
nativeauthenticator/tests/test_authenticator.py
nativeauthenticator/tests/test_orm.py
jupyterhub_nativeauthenticator-1.3.0.dist-info/LICENSE
jupyterhub_nativeauthenticator-1.3.0.dist-info/METADATA
jupyterhub_nativeauthenticator-1.3.0.dist-info/WHEEL
jupyterhub_nativeauthenticator-1.3.0.dist-info/entry_points.txt
jupyterhub_nativeauthenticator-1.3.0.dist-info/top_level.txt
jupyterhub_nativeauthenticator-1.3.0.dist-info/RECORD
