Metadata-Version: 2.1
Name: jupyterhub-nativeauthenticator
Version: 1.3.0
Summary: JupyterHub Native Authenticator
Home-page: https://github.com/jupyterhub/nativeauthenticator
Author: Leticia Portella
Author-email: leportella@protonmail.com
License: 3 Clause BSD
Requires-Python: >=3.9
License-File: LICENSE
Requires-Dist: jupyterhub>=4.1.6
Requires-Dist: bcrypt
Requires-Dist: onetimepass
Provides-Extra: test
Requires-Dist: notebook>=6.4.1; extra == "test"
Requires-Dist: pytest; extra == "test"
Requires-Dist: pytest-asyncio; extra == "test"
Requires-Dist: pytest-cov; extra == "test"
